birdspotter/BirdSpotter.py
birdspotter/__init__.py
birdspotter/user_influence.py
birdspotter/utils.py
birdspotter/data/bot_repository_booster.pickle
birdspotter/data/oversampled_booster.pickle
birdspotter/data/pretrained_botness_model.xgb
birdspotter/data/standard_bot_features
birdspotter-0.1.6b1.data/scripts/birdspotter
birdspotter-0.1.6b1.dist-info/LICENSE.txt
birdspotter-0.1.6b1.dist-info/METADATA
birdspotter-0.1.6b1.dist-info/WHEEL
birdspotter-0.1.6b1.dist-info/top_level.txt
birdspotter-0.1.6b1.dist-info/RECORD
