Metadata-Version: 2.1
Name: birdspotter
Version: 0.1.6b1
Summary: A package to measure the influence and botness of twitter users, from twitter dumps
Home-page: https://github.com/behavioral-ds/BirdSpotter
Author: Rohit Ram
Author-email: rohitram96@gmail.com
License: MIT
Download-URL: https://github.com/behavioral-ds/BirdSpotter/archive/0.1.6b1.tar.gz
Keywords: twitter,influence,botness,birdspotter,dumps
Platform: UNKNOWN
Classifier: Development Status :: 4 - Beta
Classifier: Intended Audience :: Developers
Classifier: Topic :: Sociology
Classifier: Programming Language :: Python :: 3
Classifier: Programming Language :: Python :: 3.4
Classifier: Programming Language :: Python :: 3.5
Classifier: Programming Language :: Python :: 3.6
Requires-Python: >=3
Requires-Dist: tqdm
Requires-Dist: wget
Requires-Dist: simplejson
Requires-Dist: numpy
Requires-Dist: pandas
Requires-Dist: python-dateutil
Requires-Dist: pytz
Requires-Dist: scikit-learn
Requires-Dist: scipy
Requires-Dist: six
Requires-Dist: sklearn
Requires-Dist: ijson
Requires-Dist: xgboost (==0.81)
